corvis/__init__.py
corvis/corvis.py
corvis-0.0.13.dist-info/LICENSE
corvis-0.0.13.dist-info/METADATA
corvis-0.0.13.dist-info/WHEEL
corvis-0.0.13.dist-info/top_level.txt
corvis-0.0.13.dist-info/RECORD
