Metadata-Version: 2.1
Name: corvis
Version: 0.0.13
Summary: COVID-19 Rapid Visualization
Home-page: https://github.com/ThomasDarby/COVIS/
Author: Tom Darby
Author-email: tom@tmdarby.com
License: UNKNOWN
Platform: UNKNOWN
Classifier: Development Status :: 3 - Alpha
Classifier: Programming Language :: Python :: 3
Classifier: License :: OSI Approved :: MIT License
Classifier: Intended Audience :: Developers
Classifier: Operating System :: OS Independent
Requires-Python: >=3.6
Requires-Dist: us
Requires-Dist: pandas
Requires-Dist: numpy
Requires-Dist: matplotlib
